meetliveinfo/__init__.py
meetliveinfo/client.py
meetliveinfo/models/agegroup.py
meetliveinfo/models/athlete.py
meetliveinfo/models/club.py
meetliveinfo/models/entries.py
meetliveinfo/models/enums.py
meetliveinfo/models/events.py
meetliveinfo/models/events_by_session.py
meetliveinfo/models/events_by_stroke.py
meetliveinfo/models/globals.py
meetliveinfo/models/heat.py
meetliveinfo/models/medals.py
meetliveinfo/models/pointscores.py
meetliveinfo/models/record_by_event.py
meetliveinfo/models/records.py
meetliveinfo/models/results.py
meetliveinfo-1.0.3.dist-info/METADATA
meetliveinfo-1.0.3.dist-info/WHEEL
meetliveinfo-1.0.3.dist-info/RECORD
