Metadata-Version: 2.4
Name: meetliveinfo
Version: 1.0.3
Summary: Python client for Splash Meet Manager Live Info Server (HTTP/UDP)
License: MIT
Keywords: swimming,meet-manager,live-results,sports,timing
Author: LordCode
Author-email: 9999269010dddd@gmail.com
Requires-Python: >=3.11
Classifier: Programming Language :: Python :: 3
Classifier: Programming Language :: Python :: 3.11
Classifier: License :: OSI Approved :: MIT License
Classifier: Operating System :: OS Independent
Classifier: Topic :: Software Development :: Libraries
Classifier: Topic :: Internet :: WWW/HTTP
Requires-Dist: pydantic (>=2.12.5,<3.0.0)
Requires-Dist: requests (>=2.32.5,<3.0.0)
